odoo8_addon_account_auto_fy_sequence-8.0.0.1.0.99.dev10-py2.7-nspkg.pth
odoo8_addon_account_auto_fy_sequence-8.0.0.1.0.99.dev10.dist-info/DESCRIPTION.rst
odoo8_addon_account_auto_fy_sequence-8.0.0.1.0.99.dev10.dist-info/METADATA
odoo8_addon_account_auto_fy_sequence-8.0.0.1.0.99.dev10.dist-info/RECORD
odoo8_addon_account_auto_fy_sequence-8.0.0.1.0.99.dev10.dist-info/WHEEL
odoo8_addon_account_auto_fy_sequence-8.0.0.1.0.99.dev10.dist-info/metadata.json
odoo8_addon_account_auto_fy_sequence-8.0.0.1.0.99.dev10.dist-info/namespace_packages.txt
odoo8_addon_account_auto_fy_sequence-8.0.0.1.0.99.dev10.dist-info/top_level.txt
odoo_addons/account_auto_fy_sequence/README.rst
odoo_addons/account_auto_fy_sequence/__init__.py
odoo_addons/account_auto_fy_sequence/__openerp__.py
odoo_addons/account_auto_fy_sequence/i18n/account_auto_fy_sequence.pot
odoo_addons/account_auto_fy_sequence/i18n/ar.po
odoo_addons/account_auto_fy_sequence/i18n/bs.po
odoo_addons/account_auto_fy_sequence/i18n/ca.po
odoo_addons/account_auto_fy_sequence/i18n/ca_ES.po
odoo_addons/account_auto_fy_sequence/i18n/cs.po
odoo_addons/account_auto_fy_sequence/i18n/da.po
odoo_addons/account_auto_fy_sequence/i18n/de.po
odoo_addons/account_auto_fy_sequence/i18n/en_GB.po
odoo_addons/account_auto_fy_sequence/i18n/es.po
odoo_addons/account_auto_fy_sequence/i18n/es_CR.po
odoo_addons/account_auto_fy_sequence/i18n/es_EC.po
odoo_addons/account_auto_fy_sequence/i18n/es_ES.po
odoo_addons/account_auto_fy_sequence/i18n/es_MX.po
odoo_addons/account_auto_fy_sequence/i18n/es_VE.po
odoo_addons/account_auto_fy_sequence/i18n/et.po
odoo_addons/account_auto_fy_sequence/i18n/fi.po
odoo_addons/account_auto_fy_sequence/i18n/fr.po
odoo_addons/account_auto_fy_sequence/i18n/gl.po
odoo_addons/account_auto_fy_sequence/i18n/hr.po
odoo_addons/account_auto_fy_sequence/i18n/hr_HR.po
odoo_addons/account_auto_fy_sequence/i18n/hu.po
odoo_addons/account_auto_fy_sequence/i18n/id.po
odoo_addons/account_auto_fy_sequence/i18n/it.po
odoo_addons/account_auto_fy_sequence/i18n/ja.po
odoo_addons/account_auto_fy_sequence/i18n/lt.po
odoo_addons/account_auto_fy_sequence/i18n/lt_LT.po
odoo_addons/account_auto_fy_sequence/i18n/mk.po
odoo_addons/account_auto_fy_sequence/i18n/mn.po
odoo_addons/account_auto_fy_sequence/i18n/nb.po
odoo_addons/account_auto_fy_sequence/i18n/nb_NO.po
odoo_addons/account_auto_fy_sequence/i18n/nl.po
odoo_addons/account_auto_fy_sequence/i18n/nl_BE.po
odoo_addons/account_auto_fy_sequence/i18n/pl.po
odoo_addons/account_auto_fy_sequence/i18n/pt.po
